or_gym_inventory/__init__.py
or_gym_inventory/inventory_management.py
or_gym_inventory/network_management.py
or_gym_inventory/newsvendor.py
or_gym_inventory-1.0.0.dist-info/licenses/LICENSE
or_gym_inventory-1.0.0.dist-info/METADATA
or_gym_inventory-1.0.0.dist-info/WHEEL
or_gym_inventory-1.0.0.dist-info/top_level.txt
or_gym_inventory-1.0.0.dist-info/RECORD
