Metadata-Version: 2.4
Name: or_gym_inventory
Version: 1.0.0
Summary: Gymnasium-compatible implementations of classic inventory management environments (Newsvendor, Multi-Echelon, Network) based on OR-Gym.
Author-email: Reza Barati <r2barati@torontomu.ca>
License-Expression: MIT
Project-URL: Homepage, https://github.com/r2barati/or-gym-inventory-pkg
Project-URL: Bug Tracker, https://github.com/r2barati/or-gym-inventory-pkg/issues
Keywords: reinforcement learning,operations research,inventory management,gymnasium,rl
Classifier: Development Status :: 4 - Beta
Classifier: Intended Audience :: Developers
Classifier: Intended Audience :: Science/Research
Classifier: Programming Language :: Python :: 3
Classifier: Programming Language :: Python :: 3.8
Classifier: Programming Language :: Python :: 3.9
Classifier: Programming Language :: Python :: 3.10
Classifier: Programming Language :: Python :: 3.11
Classifier: Operating System :: OS Independent
Classifier: Topic :: Scientific/Engineering :: Artificial Intelligence
Classifier: Topic :: Software Development :: Libraries :: Python Modules
Requires-Python: >=3.8
License-File: LICENSE
Requires-Dist: gymnasium>=0.26.0
Requires-Dist: numpy
Requires-Dist: scipy
Requires-Dist: pandas
Requires-Dist: networkx
Provides-Extra: examples
Requires-Dist: matplotlib; extra == "examples"
Requires-Dist: seaborn; extra == "examples"
Provides-Extra: sb3
Requires-Dist: stable-baselines3[extra]>=2.0.0; extra == "sb3"
Provides-Extra: rllib
Requires-Dist: ray[rllib]>=2.0.0; extra == "rllib"
Provides-Extra: dev
Requires-Dist: or_gym_inventory[examples,rllib,sb3]; extra == "dev"
Requires-Dist: pytest; extra == "dev"
Dynamic: license-file
